Workbook
Name aporte: 'DIO - Investiments'!$D$16
Name patrimonio_acumulado: 'DIO - Investiments'!$D$19
Name qtd_anos: 'DIO - Investiments'!$D$17
Name rendimento_carteira: 'DIO - Investiments'!$D$12
Name salario: 'DIO - Investiments'!$D$11
Name sugestao_investimento: 'DIO - Investiments'!$D$13
Name taxa_mensal: 'DIO - Investiments'!$D$18

Sheet DIO - Investiments
B10: CONFIGURAÇÕES
B11: Salário | D11: 3500
B12: Rendimento Carteira | D12: 0.006
B13: Sugestão de Investimento | D13: =D11*30% -> 1050
B15: INVESTIMENTO MENSAL
B16: Quanto investir por mês? | D16: 560
B17: Por quantos anos? | D17: 5
B18: Taxa de Rendimento mensal? | D18: 0.01079
B19: Patrimônio acumulado | D19: =FV(taxa_mensal,qtd_anos*12,aporte*-1) -> 46915.072
B20: Dividendos Mensais | D20: =patrimonio_acumulado*rendimento_carteira -> 281.49043
B22: CENÁRIOS | D22: Dividendo
A23: 2 | B23: Quanto em 2 anos? | C23: =FV($D$18,A$23*12,$D$16*-1) -> 15247.471 | D23: =C23*rendimento_carteira -> 91.484828
A24: 5 | B24: Quanto em 5 anos? | C24: =FV($D$18,A$24*12,$D$16*-1) -> 46915.072 | D24: =C24*rendimento_carteira -> 281.49043
A25: 10 | B25: Quanto em 10 anos? | C25: =FV($D$18,A$25*12,$D$16*-1) -> 136239.16 | D25: =C25*rendimento_carteira -> 817.43495
A26: 20 | B26: Quanto em 20 anos? | C26: =FV($D$18,A$26*12,$D$16*-1) -> 630111.1 | D26: =C26*rendimento_carteira -> 3780.6666
A27: 30 | B27: Quanto em 30 anos? | C27: =FV($D$18,A$27*12,$D$16*-1) -> 2420415 | D27: =C27*rendimento_carteira -> 14522.49
B29: Perfil | C29: Conservador
B30: VALOR A SER INVESTIDO POR MÊS | C30: =aporte -> 560
B32: TIPO DE FII | C32: Percentual Sugerido | D32: Valores
B33: PAPEL | C33: =VLOOKUP($C$29&"-"&B33,'Perfis Porcentagem'!$A:$D,4,FALSE) -> 0.3 | D33: =C33*$C$30 -> 168
B34: TIJOLO | C34: =VLOOKUP($C$29&"-"&B34,'Perfis Porcentagem'!$A:$D,4,FALSE) -> 0.5 | D34: =C34*$C$30 -> 280
B35: HÍBRIDOS | C35: =VLOOKUP($C$29&"-"&B35,'Perfis Porcentagem'!$A:$D,4,FALSE) -> 0.1 | D35: =C35*$C$30 -> 56
B36: FOFs | C36: =VLOOKUP($C$29&"-"&B36,'Perfis Porcentagem'!$A:$D,4,FALSE) -> 0.05 | D36: =C36*$C$30 -> 28
B37: DESENVOLVIMENTO | C37: =VLOOKUP($C$29&"-"&B37,'Perfis Porcentagem'!$A:$D,4,FALSE) -> 0.05 | D37: =C37*$C$30 -> 28
B38: HOTELARIAS | C38: =VLOOKUP($C$29&"-"&B38,'Perfis Porcentagem'!$A:$D,4,FALSE) -> 0 | D38: =C38*$C$30 -> 0
D39: =SUM(D33:D38) -> 560

Sheet Perfis Porcentagem
A2: Chave | B2: PERFIL | C2: TIPO DE FII | D2: %
A3: =B3&"-"&C3 -> Conservador-PAPEL | B3: Conservador | C3: PAPEL | D3: 0.3
A4: =B4&"-"&C4 -> Conservador-TIJOLO | B4: Conservador | C4: TIJOLO | D4: 0.5
A5: =B5&"-"&C5 -> Conservador-HÍBRIDOS | B5: Conservador | C5: HÍBRIDOS | D5: 0.1
A6: =B6&"-"&C6 -> Conservador-FOFs | B6: Conservador | C6: FOFs | D6: 0.05
A7: =B7&"-"&C7 -> Conservador-DESENVOLVIMENTO | B7: Conservador | C7: DESENVOLVIMENTO | D7: 0.05
A8: =B8&"-"&C8 -> Conservador-HOTELARIAS | B8: Conservador | C8: HOTELARIAS | D8: 0
A9: =B9&"-"&C9 -> Moderado-PAPEL | B9: Moderado | C9: PAPEL | D9: 0.32
A10: =B10&"-"&C10 -> Moderado-TIJOLO | B10: Moderado | C10: TIJOLO | D10: 0.35
A11: =B11&"-"&C11 -> Moderado-HÍBRIDOS | B11: Moderado | C11: HÍBRIDOS | D11: 0.08
A12: =B12&"-"&C12 -> Moderado-FOFs | B12: Moderado | C12: FOFs | D12: 0.05
A13: =B13&"-"&C13 -> Moderado-DESENVOLVIMENTO | B13: Moderado | C13: DESENVOLVIMENTO | D13: 0.1
A14: =B14&"-"&C14 -> Moderado-HOTELARIAS | B14: Moderado | C14: HOTELARIAS | D14: 0.1
... A20: =B20&"-"&C20 -> Agressivo-HOTELARIAS | B20: Agressivo | C20: HOTELARIAS | D20: 0.1
